isolate/__init__.py
isolate/_isolate_version.py
isolate/_version.py
isolate/logger.py
isolate/logs.py
isolate/py.typed
isolate/registry.py
isolate/backends/__init__.py
isolate/backends/_base.py
isolate/backends/common.py
isolate/backends/conda.py
isolate/backends/container.py
isolate/backends/local.py
isolate/backends/pyenv.py
isolate/backends/remote.py
isolate/backends/settings.py
isolate/backends/virtualenv.py
isolate/common/__init__.py
isolate/common/timestamp.py
isolate/connections/__init__.py
isolate/connections/common.py
isolate/connections/_local/__init__.py
isolate/connections/_local/_base.py
isolate/connections/_local/agent_startup.py
isolate/connections/grpc/__init__.py
isolate/connections/grpc/_base.py
isolate/connections/grpc/agent.py
isolate/connections/grpc/configuration.py
isolate/connections/grpc/interface.py
isolate/connections/grpc/definitions/__init__.py
isolate/connections/grpc/definitions/agent.proto
isolate/connections/grpc/definitions/agent_pb2.py
isolate/connections/grpc/definitions/agent_pb2.pyi
isolate/connections/grpc/definitions/agent_pb2_grpc.py
isolate/connections/grpc/definitions/common.proto
isolate/connections/grpc/definitions/common_pb2.py
isolate/connections/grpc/definitions/common_pb2.pyi
isolate/connections/grpc/definitions/common_pb2_grpc.py
isolate/connections/ipc/__init__.py
isolate/connections/ipc/_base.py
isolate/connections/ipc/agent.py
isolate/server/__init__.py
isolate/server/health_server.py
isolate/server/interface.py
isolate/server/server.py
isolate/server/definitions/__init__.py
isolate/server/definitions/server.proto
isolate/server/definitions/server_pb2.py
isolate/server/definitions/server_pb2.pyi
isolate/server/definitions/server_pb2_grpc.py
isolate/server/health/__init__.py
isolate/server/health/health.proto
isolate/server/health/health_pb2.py
isolate/server/health/health_pb2.pyi
isolate/server/health/health_pb2_grpc.py
isolate-0.23.0.dist-info/licenses/LICENSE
isolate-0.23.0.dist-info/METADATA
isolate-0.23.0.dist-info/WHEEL
isolate-0.23.0.dist-info/entry_points.txt
isolate-0.23.0.dist-info/top_level.txt
isolate-0.23.0.dist-info/RECORD
