Metadata-Version: 2.4
Name: isolate
Version: 0.23.0
Summary: Managed isolated environments for Python
Author-email: Features & Labels <hello@fal.ai>
Project-URL: Issues, https://github.com/fal-ai/isolate/issues
Project-URL: Source, https://github.com/fal-ai/isolate
Requires-Python: >=3.8
License-File: LICENSE
Requires-Dist: grpcio<2,>=1.64.0
Requires-Dist: protobuf>=3.20.0
Requires-Dist: tblib<3.2.0,>=1.7.0
Requires-Dist: platformdirs
Requires-Dist: importlib-metadata>=4.4; python_version < "3.10"
Provides-Extra: build
Requires-Dist: virtualenv>=20.4; extra == "build"
Requires-Dist: PyYAML>=6.0; extra == "build"
Provides-Extra: test
Requires-Dist: isolate[build]; extra == "test"
Requires-Dist: pytest; extra == "test"
Requires-Dist: cloudpickle>=2.2.0; extra == "test"
Requires-Dist: dill>=0.3.5.1; extra == "test"
Requires-Dist: flaky; extra == "test"
Provides-Extra: dev
Requires-Dist: isolate[test]; extra == "dev"
Requires-Dist: grpcio-tools==1.64.0; extra == "dev"
Dynamic: license-file
